cimsim/__init__.py
cimsim/client.py
cimsim-2.1.1.dist-info/WHEEL
cimsim-2.1.1.dist-info/METADATA
cimsim-2.1.1.dist-info/RECORD
