Metadata-Version: 2.1
Name: cimsim
Version: 2.1.1
Summary: 
Author: Airat
Author-email: airat_vi@mail.ru
Requires-Python: >=3.5,<4.0
Classifier: Programming Language :: Python :: 3
Classifier: Programming Language :: Python :: 3.5
Classifier: Programming Language :: Python :: 3.6
Classifier: Programming Language :: Python :: 3.7
Requires-Dist: requests
